alfacrm/__init__.py
alfacrm/client.py
alfacrm/py.typed
alfacrm/core/__init__.py
alfacrm/core/api.py
alfacrm/core/auth.py
alfacrm/core/entity_manager.py
alfacrm/core/exceptions.py
alfacrm/core/page.py
alfacrm/core/paginator.py
alfacrm/core/utils.py
alfacrm/entities/__init__.py
alfacrm/entities/base.py
alfacrm/entities/branch.py
alfacrm/entities/cgi.py
alfacrm/entities/communication.py
alfacrm/entities/customer.py
alfacrm/entities/customer_tariff.py
alfacrm/entities/discount.py
alfacrm/entities/group.py
alfacrm/entities/lead_reject.py
alfacrm/entities/lead_source.py
alfacrm/entities/lead_status.py
alfacrm/entities/lesson.py
alfacrm/entities/lesson_type.py
alfacrm/entities/location.py
alfacrm/entities/log.py
alfacrm/entities/pay.py
alfacrm/entities/pay_account.py
alfacrm/entities/pay_item.py
alfacrm/entities/pay_item_category.py
alfacrm/entities/regular_lesson.py
alfacrm/entities/room.py
alfacrm/entities/study_status.py
alfacrm/entities/subject.py
alfacrm/entities/tariff.py
alfacrm/entities/task.py
alfacrm/entities/webhook.py
alfacrm/managers/__init__.py
alfacrm/managers/branch.py
alfacrm/managers/cgi.py
alfacrm/managers/communication.py
alfacrm/managers/customer.py
alfacrm/managers/customer_tariff.py
alfacrm/managers/discount.py
alfacrm/managers/group.py
alfacrm/managers/lead_reject.py
alfacrm/managers/lead_source.py
alfacrm/managers/lead_status.py
alfacrm/managers/lesson.py
alfacrm/managers/lesson_type.py
alfacrm/managers/location.py
alfacrm/managers/log.py
alfacrm/managers/pay.py
alfacrm/managers/pay_account.py
alfacrm/managers/pay_item.py
alfacrm/managers/pay_item_category.py
alfacrm/managers/regular_lesson.py
alfacrm/managers/room.py
alfacrm/managers/study_status.py
alfacrm/managers/subject.py
alfacrm/managers/tariff.py
alfacrm/managers/task.py
alfacrm-0.1.3.dist-info/METADATA
alfacrm-0.1.3.dist-info/WHEEL
alfacrm-0.1.3.dist-info/RECORD
