Metadata-Version: 2.4
Name: alfacrm
Version: 0.1.3
Summary: Is an asynchronous implementation for AlfaCRM API
Project-URL: Homepage, https://github.com/Airumian/alfacrm
Project-URL: Repository, https://github.com/Airumian/alfacrm
Project-URL: Issue Tracker, https://github.com/Airumian/alfacrm/issues
Requires-Python: >=3.12.7
Requires-Dist: aiohttp>=3.12.15
Requires-Dist: pydantic>=2.11.7
